django_crypto_fields/__init__.py
django_crypto_fields/admin/__init__.py
django_crypto_fields/admin/crypt_model_admin.py
django_crypto_fields/admin/formfield_overrides.py
django_crypto_fields/admin_site.py
django_crypto_fields/apps.py
django_crypto_fields/cipher/__init__.py
django_crypto_fields/cipher/cipher.py
django_crypto_fields/cipher/cipher_parser.py
django_crypto_fields/constants.py
django_crypto_fields/cryptor.py
django_crypto_fields/encoding.py
django_crypto_fields/exceptions.py
django_crypto_fields/field_cryptor.py
django_crypto_fields/fields/__init__.py
django_crypto_fields/fields/base_aes_field.py
django_crypto_fields/fields/base_field.py
django_crypto_fields/fields/base_rsa_field.py
django_crypto_fields/fields/encrypted_char_field.py
django_crypto_fields/fields/encrypted_date_field.py
django_crypto_fields/fields/encrypted_datetime_field.py
django_crypto_fields/fields/encrypted_decimal_field.py
django_crypto_fields/fields/encrypted_integer_field.py
django_crypto_fields/fields/encrypted_text_field.py
django_crypto_fields/fields/firstname_field.py
django_crypto_fields/fields/identity_field.py
django_crypto_fields/fields/lastname_field.py
django_crypto_fields/key_path/__init__.py
django_crypto_fields/key_path/key_path.py
django_crypto_fields/key_path/persist_key_path_or_raise.py
django_crypto_fields/keys/__init__.py
django_crypto_fields/keys/keys.py
django_crypto_fields/keys/utils.py
django_crypto_fields/locale/sw/LC_MESSAGES/django.mo
django_crypto_fields/locale/sw/LC_MESSAGES/django.po
django_crypto_fields/mask_encrypted.py
django_crypto_fields/migrations/0001_initial.py
django_crypto_fields/migrations/0001_squashed_0011_delete_keyreference.py
django_crypto_fields/migrations/0002_auto_20190303_2341.py
django_crypto_fields/migrations/0002_crypt_cipher_mode.py
django_crypto_fields/migrations/0003_alter_crypt_cipher_mode.py
django_crypto_fields/migrations/0003_auto_20161124_1835.py
django_crypto_fields/migrations/0004_alter_crypt_device_created_and_more.py
django_crypto_fields-1.2.0.dist-info/licenses/LICENSE
django_crypto_fields-1.2.0.dist-info/WHEEL
django_crypto_fields-1.2.0.dist-info/METADATA
django_crypto_fields-1.2.0.dist-info/RECORD
