Metadata-Version: 2.4
Name: django-crypto-fields
Version: 1.2.0
Summary: Add encrypted field classes and more to your Django models
Keywords: django,clinicedc,edc,clinical trials,research,data management,esource,encryption,security
Author: Erik van Widenfelt
Author-email: Erik van Widenfelt <ew2789@gmail.com>
License-Expression: GPL-3.0-or-later
License-File: LICENSE
Classifier: Development Status :: 5 - Production/Stable
Classifier: Framework :: Django
Classifier: Framework :: Django :: 5.2
Classifier: Intended Audience :: Developers
Classifier: Operating System :: OS Independent
Classifier: Programming Language :: Python :: 3.12
Classifier: Programming Language :: Python :: 3.13
Requires-Dist: django-audit-fields>=2.0.2
Requires-Dist: django-extensions>=4.1
Requires-Dist: django-revision>=1.0.0
Requires-Dist: pycryptodomex>=3.23.0
Requires-Dist: python-dateutil>=2.9.0.post0
Requires-Dist: tqdm>=4.67.1
Maintainer: Erik van Widenfelt
Maintainer-email: Erik van Widenfelt <ew2789@gmail.com>
Requires-Python: >=3.12, <3.14
Project-URL: Changelog, https://github.com/erikvw/django-crypto-fields/blob/main/CHANGES
Project-URL: Documentation, https://django-crypto-fields.readthedocs.io/en/latest/
Project-URL: Homepage, https://github.com/erikvw/django-crypto-fields
Project-URL: Repository, https://github.com/erikvw/django-crypto-fields.git
